[{"image": "bowl_verb-move_around_P20-R04-ContinentalBreakfast-609860-611879-F014631-F014691_f1.jpg", "annotations": [{"label": "v_bowl", "coordinates": {"x": 367.4230769230769, "y": 271.64285714285717, "width": 141.1538461538462, "height": 136.71428571428567}}, {"label": "hand", "coordinates": {"x": 449.3461538461538, "y": 248.78571428571433, "width": 251.0, "height": 213.0}}, {"label": "strainer", "coordinates": {"x": 193.8461538461538, "y": 226.78571428571433, "width": 220.0, "height": 177.0}}, {"label": "cooking_utensil", "coordinates": {"x": 254.3461538461538, "y": 384.64285714285717, "width": 87.0, "height": 190.71428571428567}}, {"label": "cooking_utensil", "coordinates": {"x": 328.8461538461538, "y": 414.78571428571433, "width": 66.0, "height": 125.0}}, {"label": "cooking_utensil", "coordinates": {"x": 446.8461538461538, "y": 76.7857142857143, "width": 130.0, "height": 143.0}}, {"label": "pan", "coordinates": {"x": 507.3461538461538, "y": 395.78571428571433, "width": 233.0, "height": 165.0}}, {"label": "seasoning_container", "coordinates": {"x": 302.3461538461538, "y": 127.7857142857143, "width": 109.0, "height": 155.0}}, {"label": "cup", "coordinates": {"x": 156.5, "y": 410.7894736842105, "width": 217.0, "height": 138.4210526315789}}]}]