[{"image": "bread_verb-take_bread_verb-take_P17-R03-BaconAndEggs-896500-899500-F021509-F021595_f1_f2.jpg", "annotations": [{"label": "v_bread", "coordinates": {"x": 327.4230769230769, "y": 458.14285714285717, "width": 155.1538461538462, "height": 43.714285714285666}}, {"label": "hand", "coordinates": {"x": 238.8461538461538, "y": 447.64285714285717, "width": 90.0, "height": 64.71428571428567}}, {"label": "hand", "coordinates": {"x": 531.3461538461538, "y": 367.64285714285717, "width": 161.0, "height": 224.71428571428567}}, {"label": "bread_container", "coordinates": {"x": 396.8461538461538, "y": 363.28571428571433, "width": 176.0, "height": 204.0}}, {"label": "seasoning_container", "coordinates": {"x": 113.84615384615384, "y": 227.78571428571433, "width": 65.99999999999994, "height": 91.0}}, {"label": "condiment_container", "coordinates": {"x": 188.4230769230769, "y": 269.93233082706774, "width": 71.15384615384619, "height": 124.70676691729324}}, {"label": "condiment_container", "coordinates": {"x": 122.92307692307692, "y": 335.93233082706774, "width": 92.15384615384616, "height": 123.29323308270676}}, {"label": "condiment_container", "coordinates": {"x": 40.5, "y": 214.93233082706772, "width": 81.0, "height": 120.70676691729324}}, {"label": "condiment_container", "coordinates": {"x": 250.5, "y": 292.5789473684211, "width": 75.0, "height": 98.0}}, {"label": "condiment_container", "coordinates": {"x": 201.0, "y": 378.0789473684211, "width": 90.0, "height": 91.0}}, {"label": "condiment_container", "coordinates": {"x": 258.5, "y": 174.0789473684211, "width": 65.0, "height": 91.0}}]}]