[{"image": "drawer_verb-close_P21-R06-GreekSalad-465941-467588-F011178-F011227_f1.jpg", "annotations": [{"label": "water", "coordinates": {"x": 472.8461538461538, "y": 201.28571428571433, "width": 112.0, "height": 178.0}}, {"label": "fridge_drawer", "coordinates": {"x": 398.8461538461538, "y": 419.14285714285717, "width": 458.0, "height": 121.71428571428567}}, {"label": "fridge", "coordinates": {"x": 321.4230769230769, "y": 240.14285714285714, "width": 637.1538461538462, "height": 479.71428571428567}}, {"label": "tomato_container", "coordinates": {"x": 200.3461538461538, "y": 163.7857142857143, "width": 149.0, "height": 75.0}}, {"label": "cheese_container", "coordinates": {"x": 258.8461538461538, "y": 313.78571428571433, "width": 102.0, "height": 75.0}}, {"label": "condiment_container", "coordinates": {"x": 326.5, "y": 223.5789473684211, "width": 69.0, "height": 124.0}}, {"label": "condiment_container", "coordinates": {"x": 402.5, "y": 226.0789473684211, "width": 77.0, "height": 157.0}}]}]