[{"image": "eating_utensil_verb-put_eating_utensil_verb-put_P19-R04-ContinentalBreakfast-159685-162133-F003826-F003898_f1_f2.jpg", "annotations": [{"label": "v_eating_utensil", "coordinates": {"x": 246.5, "y": 319.2894736842105, "width": 149.0, "height": 89.4210526315789}}, {"label": "hand", "coordinates": {"x": 365.0, "y": 391.7894736842105, "width": 218.0, "height": 176.4210526315789}}, {"label": "hand", "coordinates": {"x": 70.0, "y": 306.0789473684211, "width": 136.0, "height": 187.0}}, {"label": "plate", "coordinates": {"x": 212.5, "y": 342.5789473684211, "width": 241.0, "height": 194.0}}, {"label": "cup", "coordinates": {"x": 328.5, "y": 90.0789473684211, "width": 245.0, "height": 171.0}}, {"label": "cabinet", "coordinates": {"x": 314.5, "y": 241.78947368421055, "width": 625.0, "height": 476.4210526315789}}]}]