[{"image": "egg_verb-mix_egg_verb-mix_P22-R03-BaconAndEggs-603561-605109-F014482-F014526_f1_f2.jpg", "annotations": [{"label": "v_egg", "coordinates": {"x": 289.0, "y": 276.7894736842105, "width": 178.0, "height": 149.5789473684211}}, {"label": "eating_utensil", "coordinates": {"x": 476.0, "y": 244.0789473684211, "width": 294.0, "height": 77.0}}, {"label": "hand", "coordinates": {"x": 537.5, "y": 345.7894736842105, "width": 183.0, "height": 268.4210526315789}}, {"label": "hand", "coordinates": {"x": 128.5, "y": 342.7894736842105, "width": 163.0, "height": 274.4210526315789}}, {"label": "bowl", "coordinates": {"x": 298.5, "y": 276.0789473684211, "width": 265.0, "height": 275.0}}, {"label": "stove", "coordinates": {"x": 63.0, "y": 226.0789473684211, "width": 126.0, "height": 449.0}}]}]