[{"image": "mixture_verb-mix_mixture_verb-mix_OP01-R03-BaconAndEggs-308640-310270-F007403-F007451_f1_f2.jpg", "annotations": [{"label": "v_mixture", "coordinates": {"x": 308.5, "y": 331.7894736842105, "width": 165.0, "height": 167.5789473684211}}, {"label": "pan", "coordinates": {"x": 239.0, "y": 335.0789473684211, "width": 382.0, "height": 251.0}}, {"label": "cooking_utensil", "coordinates": {"x": 513.0, "y": 344.5789473684211, "width": 254.0, "height": 140.0}}, {"label": "pot", "coordinates": {"x": 475.0, "y": 114.5789473684211, "width": 326.0, "height": 222.0}}, {"label": "hand", "coordinates": {"x": 52.5, "y": 381.2894736842105, "width": 103.0, "height": 197.4210526315789}}, {"label": "stove", "coordinates": {"x": 322.5, "y": 241.78947368421055, "width": 635.0, "height": 476.4210526315789}}]}]